Min_Test/test1.py
Min_Test/test2.py
Min_Test-0.0.0.3.dist-info/METADATA
Min_Test-0.0.0.3.dist-info/WHEEL
Min_Test-0.0.0.3.dist-info/top_level.txt
Min_Test-0.0.0.3.dist-info/RECORD
